psgdemos/CONTRIBUTING.md
psgdemos/LICENSE.txt
psgdemos/README.md
psgdemos/__init__.py
psgdemos/__main__.py
psgdemos/psgdemos.ico
psgdemos/psgdemos.py
psgdemos/screenshot.png
psgdemos/demo_programs/Browser_START_HERE_Demo_Programs_Browser.py
psgdemos/demo_programs/CONTRIBUTING.md
psgdemos/demo_programs/Demo_All_Elements.py
psgdemos/demo_programs/Demo_All_Elements_Simple.py
psgdemos/demo_programs/Demo_Animated_GIFs.py
psgdemos/demo_programs/Demo_Animated_GIFs_Using_PIL.py
psgdemos/demo_programs/Demo_Auto_Save_Window_Position.py
psgdemos/demo_programs/Demo_Bar_Chart.py
psgdemos/demo_programs/Demo_Base64_Image_Encoder.py
psgdemos/demo_programs/Demo_Base64_Single_Image_Encoder.py
psgdemos/demo_programs/Demo_Borderless_Window.py
psgdemos/demo_programs/Demo_Button_Can_Button_Images.py
psgdemos/demo_programs/Demo_Button_Click.py
psgdemos/demo_programs/Demo_Button_Events_From_Browse.py
psgdemos/demo_programs/Demo_Button_Func_Calls.py
psgdemos/demo_programs/Demo_Button_Simulated_With_Highlighting_Using_Bind.py
psgdemos/demo_programs/Demo_Button_States.py
psgdemos/demo_programs/Demo_Button_Toggle.py
psgdemos/demo_programs/Demo_Button_Toggle2.py
psgdemos/demo_programs/Demo_Button_Toggle_Simple_Graphic.py
psgdemos/demo_programs/Demo_Buttons_Base64_Shaded.py
psgdemos/demo_programs/Demo_Buttons_Base64_Simple.py
psgdemos/demo_programs/Demo_Buttons_Base64_User_Settings.py
psgdemos/demo_programs/Demo_Buttons_Mac.py
psgdemos/demo_programs/Demo_Buttons_Nice_Graphics.py
psgdemos/demo_programs/Demo_Buttons_Realtime.py
psgdemos/demo_programs/Demo_CLI_or_GUI.py
psgdemos/demo_programs/Demo_Calendar.py
psgdemos/demo_programs/Demo_Canvas.py
psgdemos/demo_programs/Demo_Chat.py
psgdemos/demo_programs/Demo_Chat_With_History.py
psgdemos/demo_programs/Demo_Chatterbot.py
psgdemos/demo_programs/Demo_Chatterbot_With_TTS.py
psgdemos/demo_programs/Demo_Checkboxes_Custom.py
psgdemos/demo_programs/Demo_Class_Wrapper.py
psgdemos/demo_programs/Demo_Close_Attempted_Event.py
psgdemos-5.1.1.dist-info/LICENSE.txt
psgdemos-5.1.1.dist-info/METADATA
psgdemos-5.1.1.dist-info/WHEEL
psgdemos-5.1.1.dist-info/entry_points.txt
psgdemos-5.1.1.dist-info/top_level.txt
psgdemos-5.1.1.dist-info/RECORD
